CHANGELOG.md
MANIFEST.in
Makefile
README.md
README.rst
pylintrc
requirements-test.txt
requirements.txt
setup.py
tox.ini
EatMe.egg-info/PKG-INFO
EatMe.egg-info/SOURCES.txt
EatMe.egg-info/dependency_links.txt
EatMe.egg-info/entry_points.txt
EatMe.egg-info/pbr.json
EatMe.egg-info/requires.txt
EatMe.egg-info/top_level.txt
eatme/__init__.py
eatme/cli.py
eatme/git.py
eatme/hg.py
eatme.egg-info/SOURCES.txt
tests/__init__.py
tests/test_cli.py
tests/test_git.py
tests/test_hg.py