Metadata-Version: 1.0
Name: eatme
Version: 0.1.1
Summary: EatMe Utility
Home-page: https://github.com/kulapard/eatme
Author: Taras Drapalyuk
Author-email: taras@drapalyuk.com
License: UNKNOWN
Platform: UNKNOWN
